{
  "type": "Feature",
  "properties": {
    "marker-color": "#a5cb39",
    "marker-size": "medium",
    "marker-symbol": "",
    "title": "REST Fest US @ 101 N Main St."
  },
  "geometry": {
    "type": "Point",
    "coordinates": [
      -82.39959061145781,
      34.85193969456589
    ]
  }
}
